{"id":"src\\react-dom\\render.js","dependencies":[{"name":"d:\\Workspace\\LestaSan_js_fullstack\\react\\diff\\package.json","includedInParent":true,"mtime":1533282179919},{"name":"d:\\Workspace\\LestaSan_js_fullstack\\react\\diff\\.babelrc","includedInParent":true,"mtime":1533281977229},{"name":"./dom.js","loc":{"line":8,"column":29},"parent":"d:\\Workspace\\LestaSan_js_fullstack\\react\\diff\\src\\react-dom\\render.js","resolved":"d:\\Workspace\\LestaSan_js_fullstack\\react\\diff\\src\\react-dom\\dom.js"}],"generated":{"js":"'use strict';\n\nObject.defineProperty(exports, \"__esModule\", {\n    value: true\n});\nexports.render = render;\n\nvar _dom = require('./dom.js');\n\nfunction _render(vnode) {\n    // 1. 递归 将结点转为DOM，子结点递归，要有出口  即文本节点时，结束\n    // 2. 结点类型： 三种：\n    // 文本结点 createTextNode() 在递归里结束  return createTextNode()\n    // 标签结点 createElement 有attrs设置 children设置(递归 _render)\n    // 3. Component类型  render(return jsx)  组件返回jsx  再在外层父结点render()一次\n    if (vnode === undefined || vnode === null || typeof vnode === 'boolean') vnode = '';\n\n    if (typeof vnode === 'string') {\n        var textNode = document.createTextNode(vnode);\n        return textNode;\n    }\n\n    var dom = document.createElement(vnode.tag);\n    if (vnode.attrs) {\n        Object.keys(vnode.attrs).forEach(function (key) {\n            var value = vnode.attrs[key];\n            (0, _dom.setAttribute)(dom, key, value);\n        });\n    }\n\n    if (vnode.children) {\n        vnode.children.forEach(function (child) {\n            return render(child, dom);\n        });\n    }\n\n    return dom;\n}\n/**\r\n * 将虚拟DOM 变为真实DOM\r\n * @params vnode 虚拟DOM\r\n * @return 返回DOM\r\n * \r\n */\nfunction render(vnode, container) {\n    console.log(vnode, container);\n    return container.appendChild(_render(vnode));\n}","map":{"mappings":[{"name":"render","generated":{"line":6,"column":8},"source":"src\\react-dom\\render.js","original":{"line":38,"column":16}},{"name":"render","generated":{"line":6,"column":17},"source":"src\\react-dom\\render.js","original":{"line":38,"column":16}},{"generated":{"line":8,"column":0},"source":"src\\react-dom\\render.js","original":{"line":8,"column":0}},{"generated":{"line":10,"column":0},"source":"src\\react-dom\\render.js","original":{"line":9,"column":0}},{"name":"_render","generated":{"line":10,"column":9},"source":"src\\react-dom\\render.js","original":{"line":9,"column":9}},{"generated":{"line":10,"column":16},"source":"src\\react-dom\\render.js","original":{"line":9,"column":0}},{"name":"vnode","generated":{"line":10,"column":17},"source":"src\\react-dom\\render.js","original":{"line":9,"column":18}},{"generated":{"line":10,"column":22},"source":"src\\react-dom\\render.js","original":{"line":9,"column":0}},{"generated":{"line":10,"column":24},"source":"src\\react-dom\\render.js","original":{"line":9,"column":25}},{"generated":{"line":11,"column":0},"source":"src\\react-dom\\render.js","original":{"line":10,"column":4}},{"generated":{"line":12,"column":0},"source":"src\\react-dom\\render.js","original":{"line":11,"column":4}},{"generated":{"line":13,"column":0},"source":"src\\react-dom\\render.js","original":{"line":12,"column":8}},{"generated":{"line":14,"column":0},"source":"src\\react-dom\\render.js","original":{"line":13,"column":8}},{"generated":{"line":15,"column":0},"source":"src\\react-dom\\render.js","original":{"line":14,"column":8}},{"generated":{"line":16,"column":0},"source":"src\\react-dom\\render.js","original":{"line":15,"column":4}},{"name":"vnode","generated":{"line":16,"column":8},"source":"src\\react-dom\\render.js","original":{"line":15,"column":8}},{"name":"undefined","generated":{"line":16,"column":18},"source":"src\\react-dom\\render.js","original":{"line":15,"column":18}},{"generated":{"line":16,"column":27},"source":"src\\react-dom\\render.js","original":{"line":15,"column":8}},{"name":"vnode","generated":{"line":16,"column":31},"source":"src\\react-dom\\render.js","original":{"line":15,"column":31}},{"generated":{"line":16,"column":41},"source":"src\\react-dom\\render.js","original":{"line":15,"column":41}},{"generated":{"line":16,"column":45},"source":"src\\react-dom\\render.js","original":{"line":15,"column":8}},{"generated":{"line":16,"column":49},"source":"src\\react-dom\\render.js","original":{"line":15,"column":49}},{"name":"vnode","generated":{"line":16,"column":56},"source":"src\\react-dom\\render.js","original":{"line":15,"column":56}},{"generated":{"line":16,"column":61},"source":"src\\react-dom\\render.js","original":{"line":15,"column":49}},{"generated":{"line":16,"column":66},"source":"src\\react-dom\\render.js","original":{"line":15,"column":66}},{"generated":{"line":16,"column":75},"source":"src\\react-dom\\render.js","original":{"line":15,"column":4}},{"name":"vnode","generated":{"line":16,"column":77},"source":"src\\react-dom\\render.js","original":{"line":15,"column":77}},{"generated":{"line":16,"column":85},"source":"src\\react-dom\\render.js","original":{"line":15,"column":85}},{"generated":{"line":16,"column":87},"source":"src\\react-dom\\render.js","original":{"line":15,"column":77}},{"generated":{"line":18,"column":0},"source":"src\\react-dom\\render.js","original":{"line":17,"column":4}},{"generated":{"line":18,"column":8},"source":"src\\react-dom\\render.js","original":{"line":17,"column":8}},{"name":"vnode","generated":{"line":18,"column":15},"source":"src\\react-dom\\render.js","original":{"line":17,"column":15}},{"generated":{"line":18,"column":20},"source":"src\\react-dom\\render.js","original":{"line":17,"column":8}},{"generated":{"line":18,"column":25},"source":"src\\react-dom\\render.js","original":{"line":17,"column":25}},{"generated":{"line":18,"column":33},"source":"src\\react-dom\\render.js","original":{"line":17,"column":4}},{"generated":{"line":18,"column":35},"source":"src\\react-dom\\render.js","original":{"line":17,"column":35}},{"generated":{"line":19,"column":0},"source":"src\\react-dom\\render.js","original":{"line":18,"column":8}},{"name":"textNode","generated":{"line":19,"column":12},"source":"src\\react-dom\\render.js","original":{"line":18,"column":12}},{"name":"document","generated":{"line":19,"column":23},"source":"src\\react-dom\\render.js","original":{"line":18,"column":23}},{"name":"createTextNode","generated":{"line":19,"column":32},"source":"src\\react-dom\\render.js","original":{"line":18,"column":32}},{"generated":{"line":19,"column":46},"source":"src\\react-dom\\render.js","original":{"line":18,"column":23}},{"name":"vnode","generated":{"line":19,"column":47},"source":"src\\react-dom\\render.js","original":{"line":18,"column":47}},{"generated":{"line":19,"column":52},"source":"src\\react-dom\\render.js","original":{"line":18,"column":23}},{"generated":{"line":19,"column":53},"source":"src\\react-dom\\render.js","original":{"line":18,"column":8}},{"generated":{"line":20,"column":0},"source":"src\\react-dom\\render.js","original":{"line":19,"column":8}},{"name":"textNode","generated":{"line":20,"column":15},"source":"src\\react-dom\\render.js","original":{"line":19,"column":15}},{"generated":{"line":20,"column":23},"source":"src\\react-dom\\render.js","original":{"line":19,"column":8}},{"generated":{"line":21,"column":0},"source":"src\\react-dom\\render.js","original":{"line":20,"column":5}},{"generated":{"line":23,"column":0},"source":"src\\react-dom\\render.js","original":{"line":22,"column":4}},{"name":"dom","generated":{"line":23,"column":8},"source":"src\\react-dom\\render.js","original":{"line":22,"column":10}},{"name":"document","generated":{"line":23,"column":14},"source":"src\\react-dom\\render.js","original":{"line":22,"column":16}},{"name":"createElement","generated":{"line":23,"column":23},"source":"src\\react-dom\\render.js","original":{"line":22,"column":25}},{"generated":{"line":23,"column":36},"source":"src\\react-dom\\render.js","original":{"line":22,"column":16}},{"name":"vnode","generated":{"line":23,"column":37},"source":"src\\react-dom\\render.js","original":{"line":22,"column":39}},{"name":"tag","generated":{"line":23,"column":43},"source":"src\\react-dom\\render.js","original":{"line":22,"column":45}},{"generated":{"line":23,"column":46},"source":"src\\react-dom\\render.js","original":{"line":22,"column":16}},{"generated":{"line":23,"column":47},"source":"src\\react-dom\\render.js","original":{"line":22,"column":4}},{"generated":{"line":24,"column":0},"source":"src\\react-dom\\render.js","original":{"line":23,"column":4}},{"name":"vnode","generated":{"line":24,"column":8},"source":"src\\react-dom\\render.js","original":{"line":23,"column":8}},{"name":"attrs","generated":{"line":24,"column":14},"source":"src\\react-dom\\render.js","original":{"line":23,"column":14}},{"generated":{"line":24,"column":19},"source":"src\\react-dom\\render.js","original":{"line":23,"column":4}},{"generated":{"line":24,"column":21},"source":"src\\react-dom\\render.js","original":{"line":23,"column":21}},{"name":"Object","generated":{"line":25,"column":0},"source":"src\\react-dom\\render.js","original":{"line":24,"column":8}},{"name":"keys","generated":{"line":25,"column":15},"source":"src\\react-dom\\render.js","original":{"line":24,"column":15}},{"generated":{"line":25,"column":19},"source":"src\\react-dom\\render.js","original":{"line":24,"column":8}},{"name":"vnode","generated":{"line":25,"column":20},"source":"src\\react-dom\\render.js","original":{"line":24,"column":20}},{"name":"attrs","generated":{"line":25,"column":26},"source":"src\\react-dom\\render.js","original":{"line":24,"column":26}},{"generated":{"line":25,"column":31},"source":"src\\react-dom\\render.js","original":{"line":24,"column":8}},{"name":"forEach","generated":{"line":25,"column":33},"source":"src\\react-dom\\render.js","original":{"line":24,"column":33}},{"generated":{"line":25,"column":40},"source":"src\\react-dom\\render.js","original":{"line":24,"column":8}},{"generated":{"line":25,"column":41},"source":"src\\react-dom\\render.js","original":{"line":24,"column":41}},{"generated":{"line":25,"column":56},"source":"src\\react-dom\\render.js","original":{"line":24,"column":48}},{"generated":{"line":26,"column":0},"source":"src\\react-dom\\render.js","original":{"line":25,"column":12}},{"name":"value","generated":{"line":26,"column":16},"source":"src\\react-dom\\render.js","original":{"line":25,"column":18}},{"name":"vnode","generated":{"line":26,"column":24},"source":"src\\react-dom\\render.js","original":{"line":25,"column":26}},{"name":"attrs","generated":{"line":26,"column":30},"source":"src\\react-dom\\render.js","original":{"line":25,"column":32}},{"generated":{"line":26,"column":35},"source":"src\\react-dom\\render.js","original":{"line":25,"column":26}},{"name":"key","generated":{"line":26,"column":36},"source":"src\\react-dom\\render.js","original":{"line":25,"column":38}},{"generated":{"line":26,"column":39},"source":"src\\react-dom\\render.js","original":{"line":25,"column":26}},{"generated":{"line":26,"column":40},"source":"src\\react-dom\\render.js","original":{"line":25,"column":12}},{"generated":{"line":27,"column":0},"source":"src\\react-dom\\render.js","original":{"line":26,"column":12}},{"name":"dom","generated":{"line":27,"column":35},"source":"src\\react-dom\\render.js","original":{"line":26,"column":25}},{"generated":{"line":27,"column":38},"source":"src\\react-dom\\render.js","original":{"line":26,"column":12}},{"name":"key","generated":{"line":27,"column":40},"source":"src\\react-dom\\render.js","original":{"line":26,"column":30}},{"generated":{"line":27,"column":43},"source":"src\\react-dom\\render.js","original":{"line":26,"column":12}},{"name":"value","generated":{"line":27,"column":45},"source":"src\\react-dom\\render.js","original":{"line":26,"column":35}},{"generated":{"line":27,"column":50},"source":"src\\react-dom\\render.js","original":{"line":26,"column":12}},{"generated":{"line":28,"column":0},"source":"src\\react-dom\\render.js","original":{"line":27,"column":9}},{"generated":{"line":28,"column":9},"source":"src\\react-dom\\render.js","original":{"line":24,"column":8}},{"generated":{"line":29,"column":0},"source":"src\\react-dom\\render.js","original":{"line":28,"column":5}},{"generated":{"line":31,"column":0},"source":"src\\react-dom\\render.js","original":{"line":30,"column":4}},{"name":"vnode","generated":{"line":31,"column":8},"source":"src\\react-dom\\render.js","original":{"line":30,"column":8}},{"name":"children","generated":{"line":31,"column":14},"source":"src\\react-dom\\render.js","original":{"line":30,"column":14}},{"generated":{"line":31,"column":22},"source":"src\\react-dom\\render.js","original":{"line":30,"column":4}},{"generated":{"line":31,"column":24},"source":"src\\react-dom\\render.js","original":{"line":30,"column":24}},{"name":"vnode","generated":{"line":32,"column":0},"source":"src\\react-dom\\render.js","original":{"line":31,"column":8}},{"name":"children","generated":{"line":32,"column":14},"source":"src\\react-dom\\render.js","original":{"line":31,"column":14}},{"generated":{"line":32,"column":22},"source":"src\\react-dom\\render.js","original":{"line":31,"column":8}},{"name":"forEach","generated":{"line":32,"column":23},"source":"src\\react-dom\\render.js","original":{"line":31,"column":23}},{"generated":{"line":32,"column":30},"source":"src\\react-dom\\render.js","original":{"line":31,"column":8}},{"generated":{"line":32,"column":31},"source":"src\\react-dom\\render.js","original":{"line":31,"column":31}},{"generated":{"line":33,"column":0},"source":"src\\react-dom\\render.js","original":{"line":31,"column":31}},{"name":"render","generated":{"line":33,"column":19},"source":"src\\react-dom\\render.js","original":{"line":31,"column":40}},{"name":"child","generated":{"line":33,"column":26},"source":"src\\react-dom\\render.js","original":{"line":31,"column":47}},{"generated":{"line":33,"column":31},"source":"src\\react-dom\\render.js","original":{"line":31,"column":40}},{"name":"dom","generated":{"line":33,"column":33},"source":"src\\react-dom\\render.js","original":{"line":31,"column":54}},{"generated":{"line":33,"column":36},"source":"src\\react-dom\\render.js","original":{"line":31,"column":40}},{"generated":{"line":33,"column":37},"source":"src\\react-dom\\render.js","original":{"line":31,"column":31}},{"generated":{"line":34,"column":0},"source":"src\\react-dom\\render.js","original":{"line":31,"column":31}},{"generated":{"line":34,"column":9},"source":"src\\react-dom\\render.js","original":{"line":31,"column":8}},{"generated":{"line":35,"column":0},"source":"src\\react-dom\\render.js","original":{"line":32,"column":5}},{"generated":{"line":37,"column":0},"source":"src\\react-dom\\render.js","original":{"line":34,"column":4}},{"name":"dom","generated":{"line":37,"column":11},"source":"src\\react-dom\\render.js","original":{"line":34,"column":11}},{"generated":{"line":37,"column":14},"source":"src\\react-dom\\render.js","original":{"line":34,"column":4}},{"generated":{"line":38,"column":0},"source":"src\\react-dom\\render.js","original":{"line":35,"column":1}},{"generated":{"line":39,"column":0},"source":"src\\react-dom\\render.js","original":{"line":2,"column":0}},{"generated":{"line":45,"column":0},"source":"src\\react-dom\\render.js","original":{"line":38,"column":7}},{"name":"render","generated":{"line":45,"column":9},"source":"src\\react-dom\\render.js","original":{"line":38,"column":16}},{"generated":{"line":45,"column":15},"source":"src\\react-dom\\render.js","original":{"line":38,"column":7}},{"name":"vnode","generated":{"line":45,"column":16},"source":"src\\react-dom\\render.js","original":{"line":38,"column":24}},{"generated":{"line":45,"column":21},"source":"src\\react-dom\\render.js","original":{"line":38,"column":7}},{"name":"container","generated":{"line":45,"column":23},"source":"src\\react-dom\\render.js","original":{"line":38,"column":31}},{"generated":{"line":45,"column":32},"source":"src\\react-dom\\render.js","original":{"line":38,"column":7}},{"generated":{"line":45,"column":34},"source":"src\\react-dom\\render.js","original":{"line":38,"column":42}},{"name":"console","generated":{"line":46,"column":0},"source":"src\\react-dom\\render.js","original":{"line":39,"column":4}},{"name":"log","generated":{"line":46,"column":12},"source":"src\\react-dom\\render.js","original":{"line":39,"column":12}},{"generated":{"line":46,"column":15},"source":"src\\react-dom\\render.js","original":{"line":39,"column":4}},{"name":"vnode","generated":{"line":46,"column":16},"source":"src\\react-dom\\render.js","original":{"line":39,"column":16}},{"generated":{"line":46,"column":21},"source":"src\\react-dom\\render.js","original":{"line":39,"column":4}},{"name":"container","generated":{"line":46,"column":23},"source":"src\\react-dom\\render.js","original":{"line":39,"column":23}},{"generated":{"line":46,"column":32},"source":"src\\react-dom\\render.js","original":{"line":39,"column":4}},{"generated":{"line":47,"column":0},"source":"src\\react-dom\\render.js","original":{"line":40,"column":4}},{"name":"container","generated":{"line":47,"column":11},"source":"src\\react-dom\\render.js","original":{"line":40,"column":11}},{"name":"appendChild","generated":{"line":47,"column":21},"source":"src\\react-dom\\render.js","original":{"line":40,"column":21}},{"generated":{"line":47,"column":32},"source":"src\\react-dom\\render.js","original":{"line":40,"column":11}},{"name":"_render","generated":{"line":47,"column":33},"source":"src\\react-dom\\render.js","original":{"line":40,"column":33}},{"name":"vnode","generated":{"line":47,"column":41},"source":"src\\react-dom\\render.js","original":{"line":40,"column":41}},{"generated":{"line":47,"column":46},"source":"src\\react-dom\\render.js","original":{"line":40,"column":33}},{"generated":{"line":47,"column":47},"source":"src\\react-dom\\render.js","original":{"line":40,"column":11}},{"generated":{"line":47,"column":48},"source":"src\\react-dom\\render.js","original":{"line":40,"column":4}},{"generated":{"line":48,"column":0},"source":"src\\react-dom\\render.js","original":{"line":41,"column":1}}],"sources":{"src\\react-dom\\render.js":"\r\n/**\r\n * 将虚拟DOM 变为真实DOM\r\n * @params vnode 虚拟DOM\r\n * @return 返回DOM\r\n * \r\n */ \r\nimport { setAttribute } from './dom.js';\r\nfunction _render (vnode) {\r\n    // 1. 递归 将结点转为DOM，子结点递归，要有出口  即文本节点时，结束\r\n    // 2. 结点类型： 三种：\r\n        // 文本结点 createTextNode() 在递归里结束  return createTextNode()\r\n        // 标签结点 createElement 有attrs设置 children设置(递归 _render)\r\n        // 3. Component类型  render(return jsx)  组件返回jsx  再在外层父结点render()一次\r\n    if (vnode === undefined || vnode === null || typeof vnode === 'boolean') vnode = '';\r\n\r\n    if (typeof vnode === 'string') {\r\n        let textNode = document.createTextNode(vnode);\r\n        return textNode;\r\n    }\r\n\r\n    const dom = document.createElement(vnode.tag);\r\n    if (vnode.attrs) {\r\n        Object.keys(vnode.attrs).forEach(key => {\r\n            const value = vnode.attrs[key];\r\n            setAttribute(dom, key, value);\r\n        })\r\n    }\r\n\r\n    if (vnode.children) {\r\n        vnode.children.forEach(child => render(child, dom));\r\n    }\r\n\r\n    return dom;\r\n}\r\n\r\n\r\nexport function render (vnode, container) {\r\n    console.log(vnode, container);\r\n    return container.appendChild(_render(vnode));\r\n}\r\n\r\n"},"lineCount":null}},"hash":"97dfeffeed3d52a8a014aaf14a606db4","cacheData":{"env":{}}}